LICENSE
MANIFEST.in
README.rst
VERSION
requirements.txt
setup.py
enc/remote.enc
enc/student2018.enc
enc/teacher2019.enc
pyedu/__init__.py
pyedu/app.py
pyedu/config.py
pyedu/manage.py
pyedu/models.py
pyedu.egg-info/PKG-INFO
pyedu.egg-info/SOURCES.txt
pyedu.egg-info/dependency_links.txt
pyedu.egg-info/not-zip-safe
pyedu.egg-info/requires.txt
pyedu.egg-info/top_level.txt
pyedu/forms/__init__.py
pyedu/forms/auth.py
pyedu/forms/lecture.py
pyedu/forms/lesson.py
pyedu/forms/task_edit.py
pyedu/forms/task_view.py
pyedu/forms/user.py
pyedu/main/__init__.py
pyedu/main/views/__init__.py
pyedu/main/views/auth.py
pyedu/main/views/main.py
pyedu/student/__init__.py
pyedu/student/views/__init__.py
pyedu/student/views/assignment.py
pyedu/student/views/lecture.py
pyedu/student/views/lesson.py
pyedu/student/views/report.py
pyedu/student/views/task.py
pyedu/teacher/__init__.py
pyedu/teacher/views/__init__.py
pyedu/teacher/views/lecture.py
pyedu/teacher/views/lesson.py
pyedu/teacher/views/task.py
pyedu/templates/base.html
pyedu/templates/index.html
pyedu/templates/login.html
pyedu/templates/settings.html
pyedu/templates/student/_lecture_table.html
pyedu/templates/student/_lesson_table.html
pyedu/templates/student/_task_table.html
pyedu/templates/student/lectures.html
pyedu/templates/student/lessons.html
pyedu/templates/student/report.html
pyedu/templates/student/tasks.html
pyedu/templates/student/view_lecture.html
pyedu/templates/student/view_lesson.html
pyedu/templates/student/view_task.html
pyedu/templates/teacher/edit_lecture.html
pyedu/templates/teacher/edit_lesson.html
pyedu/templates/teacher/edit_task.html
pyedu/util/__init__.py
pyedu/util/decorators.py
pyedu/util/info.py
pyedu/util/reports.py