Metadata-Version: 1.0
Name: pyedu
Version: 0.1.2
Summary: Leaning Python interactively
Home-page: UNKNOWN
Author: Mirko Mälicke
Author-email: mirko@maelicke-online.de
License: MIT
Platform: UNKNOWN
